ssisconv/__init__.py
ssisconverter-0.1.dist-info/LICENSE.txt
ssisconverter-0.1.dist-info/METADATA
ssisconverter-0.1.dist-info/WHEEL
ssisconverter-0.1.dist-info/top_level.txt
ssisconverter-0.1.dist-info/RECORD
